odoo10_addon_account_invoice_import_ubl-10.0.1.0.0.99.dev18-nspkg.pth
odoo/addons/account_invoice_import_ubl/README.rst
odoo/addons/account_invoice_import_ubl/__init__.py
odoo/addons/account_invoice_import_ubl/__manifest__.py
odoo/addons/account_invoice_import_ubl/demo/demo_data.xml
odoo/addons/account_invoice_import_ubl/i18n/account_invoice_import_ubl.pot
odoo/addons/account_invoice_import_ubl/i18n/fr.po
odoo/addons/account_invoice_import_ubl/i18n/pt.po
odoo/addons/account_invoice_import_ubl/i18n/sl.po
odoo/addons/account_invoice_import_ubl/static/description/icon.png
odoo/addons/account_invoice_import_ubl/tests/__init__.py
odoo/addons/account_invoice_import_ubl/tests/test_ubl.py
odoo/addons/account_invoice_import_ubl/tests/files/UBLInvoice-multitankcard-line_adjust.xml
odoo/addons/account_invoice_import_ubl/tests/files/UBLKetentest_Referentiefactuur_20150100.xml
odoo/addons/account_invoice_import_ubl/tests/files/efff_BE0505890632_160421_Inv_16117778.xml
odoo/addons/account_invoice_import_ubl/wizard/__init__.py
odoo/addons/account_invoice_import_ubl/wizard/account_invoice_import.py
odoo/addons/account_invoice_import_ubl/wizard/account_invoice_import_view.xml
odoo10_addon_account_invoice_import_ubl-10.0.1.0.0.99.dev18.dist-info/METADATA
odoo10_addon_account_invoice_import_ubl-10.0.1.0.0.99.dev18.dist-info/WHEEL
odoo10_addon_account_invoice_import_ubl-10.0.1.0.0.99.dev18.dist-info/namespace_packages.txt
odoo10_addon_account_invoice_import_ubl-10.0.1.0.0.99.dev18.dist-info/top_level.txt
odoo10_addon_account_invoice_import_ubl-10.0.1.0.0.99.dev18.dist-info/RECORD
